wechat_oa_mcp/__init__.py
wechat_oa_mcp/__main__.py
wechat_oa_mcp/cli.py
wechat_oa_mcp/server.py
wechat_oa_mcp-0.1.0.dist-info/METADATA
wechat_oa_mcp-0.1.0.dist-info/WHEEL
wechat_oa_mcp-0.1.0.dist-info/entry_points.txt
wechat_oa_mcp-0.1.0.dist-info/top_level.txt
wechat_oa_mcp-0.1.0.dist-info/RECORD
