Metadata-Version: 2.4
Name: wechat_oa_mcp
Version: 0.1.0
Summary: 微信公众号MCP管理工具 - 此 MCP 服务器仅限研究用途，禁止用于商业目的。
Home-page: 
Author: Jupiter
Author-email: Jupiter <jupiter3019@163.com>
Classifier: Programming Language :: Python :: 3
Classifier: License :: OSI Approved :: MIT License
Classifier: Operating System :: OS Independent
Requires-Python: >=3.10
Requires-Dist: fastmcp
Requires-Dist: requests
Dynamic: author
Dynamic: requires-python
